CHANGELOG.md
LICENSE
MANIFEST.in
README.md
setup.py
pnp_graphql/__init__.py
pnp_graphql/admin.py
pnp_graphql/apps.py
pnp_graphql/authentication.py
pnp_graphql/constants.py
pnp_graphql/exceptions.py
pnp_graphql/input_generator.py
pnp_graphql/models.py
pnp_graphql/schema.py
pnp_graphql/status_code.py
pnp_graphql/tests.py
pnp_graphql/type_generator.py
pnp_graphql/urls.py
pnp_graphql.egg-info/PKG-INFO
pnp_graphql.egg-info/SOURCES.txt
pnp_graphql.egg-info/dependency_links.txt
pnp_graphql.egg-info/requires.txt
pnp_graphql.egg-info/top_level.txt
pnp_graphql/migrations/0001_initial.py
pnp_graphql/migrations/0002_auto_20190814_0352.py
pnp_graphql/migrations/__init__.py
pnp_graphql/mutations/__init__.py
pnp_graphql/mutations/create_mutations.py
pnp_graphql/mutations/delete_mutations.py
pnp_graphql/mutations/update_mutations.py
pnp_graphql/utils/__init__.py
pnp_graphql/utils/class_factory.py
pnp_graphql/utils/field_mappings.py
pnp_graphql/utils/managers.py
pnp_graphql/utils/query_helpers.py